README.rst
setup.py
ox_log/__init__.py
ox_log.egg-info/PKG-INFO
ox_log.egg-info/SOURCES.txt
ox_log.egg-info/dependency_links.txt
ox_log.egg-info/entry_points.txt
ox_log.egg-info/requires.txt
ox_log.egg-info/top_level.txt
ox_log/core/__init__.py
ox_log/core/loader.py
ox_log/core/utils.py
ox_log/ui/__init__.py
ox_log/ui/flask_web_ui/__init__.py
ox_log/ui/flask_web_ui/ox_log/__init__.py
ox_log/ui/flask_web_ui/ox_log/core.py
ox_log/ui/flask_web_ui/ox_log/views.py
ox_log/ui/flask_web_ui/ox_log/static/w3.css
ox_log/ui/flask_web_ui/ox_log/templates/add_topic_form.html
ox_log/ui/flask_web_ui/ox_log/templates/drop_topic_form.html
ox_log/ui/flask_web_ui/ox_log/templates/layout.html
ox_log/ui/flask_web_ui/ox_log/templates/ox_log_display.html
ox_log/ui/flask_web_ui/ox_log/templates/ox_log_home.html
ox_log/ui/flask_web_ui/ox_log/templates/ox_log_layout.html
ox_log/ui/flask_web_ui/ox_log/templates/ox_log_problems_snippet.html
ox_log/ui/flask_web_ui/ox_log/templates/show_ox_log_data.html