Metadata-Version: 1.1
Name: ox-log
Version: 0.2
Summary: Lightweight log visualization.
Home-page: http://github.com/emin63/ox_log
Author: Emin Martinian
Author-email: emin.martinian@gmail.com
License: custom
Keywords: lightweight logging visualization
Platform: UNKNOWN
Classifier: Development Status :: 3 - Alpha
Classifier: Intended Audience :: Developers
Classifier: Programming Language :: Python :: 3
